[
  {
    "id": 1,
    "picture": "image1.jpg",
    "title": "Cozy Winter Jacket",
    "category": "Clothing",
    "category_bg": "red",
    "card_bg": "lightpink",
    "text_color": "white",
    "button_bg": "red",
    "description": "A warm and stylish winter jacket to keep you cozy during the cold months.",
    "price": 120.00
  },
  {
    "id": 2,
    "picture": "image2.jpg",
    "title": "Modern Sofa",
    "category": "Clothing",
    "category_bg": "red",
    "card_bg": "lightpink",
    "text_color": "white",
    "button_bg": "red",
    "description": "A comfortable and sleek modern sofa, perfect for any living room.",
    "price": 850.00
  },
  {
    "id": 3,
    "picture": "image3.jpg",
    "title": "Running Shoes",
    "category": "Clothing",
    "category_bg": "red",
    "card_bg": "lightpink",
    "text_color": "white",
    "button_bg": "red",
    "description": "Lightweight and durable running shoes for all your fitness needs.",
    "price": 95.00
  },
  {
    "id": 4,
    "picture": "image4.jpg",
    "title": "Smartphone",
    "category": "Education",
    "category_bg": "blue",
    "card_bg": "lightblue",
    "text_color": "white",
    "button_bg": "blue",
    "description": "The latest smartphone with cutting-edge features and sleek design.",
    "price": 699.00
  },
  {
    "id": 5,
    "picture": "image5.jpg",
    "title": "Leather Handbag",
    "category": "Education",
    "category_bg": "blue",
    "card_bg": "lightblue",
    "text_color": "white",
    "button_bg": "blue",
    "description": "A stylish leather handbag to complement your outfit.",
    "price": 250.00
  },
  {
    "id": 6,
    "picture": "image6.jpg",
    "title": "Mountain Bike",
    "category": "Education",
    "category_bg": "blue",
    "card_bg": "lightblue",
    "text_color": "white",
    "button_bg": "blue",
    "description": "A robust mountain bike for adventure enthusiasts.",
    "price": 450.00
  },
  {
    "id": 7,
    "picture": "image7.jpg",
    "title": "Electric Guitar",
    "category": "Food",
    "category_bg": "green",
    "card_bg": "lightgreen",
    "text_color": "white",
    "button_bg": "green",
    "description": "A high-quality electric guitar for aspiring musicians.",
    "price": 300.00
  },
  {
    "id": 8,
    "picture": "image8.jpg",
    "title": "Kitchen Mixer",
    "category": "Food",
    "category_bg": "green",
    "card_bg": "lightgreen",
    "text_color": "white",
    "button_bg": "green",
    "description": "A versatile kitchen mixer to simplify your cooking tasks.",
    "price": 150.00
  },
  {
    "id": 9,
    "picture": "image9.jpg",
    "title": "Yoga Mat",
    "category": "Food",
    "category_bg": "green",
    "card_bg": "lightgreen",
    "text_color": "white",
    "button_bg": "green",
    "description": "A comfortable yoga mat for your daily exercise routine.",
    "price": 30.00
  },
  {
    "id": 10,
    "picture": "image10.jpg",
    "title": "Sunglasses",
    "category": "Health",
    "category_bg": "yellow",
    "card_bg": "lightyellow",
    "text_color": "black",
    "button_bg": "yellow",
    "description": "Stylish sunglasses to protect your eyes and enhance your look.",
    "price": 75.00
  },
  {
    "id": 11,
    "picture": "image11.jpg",
    "title": "Bluetooth Speaker",
    "category": "Health",
    "category_bg": "yellow",
    "card_bg": "lightyellow",
    "text_color": "black",
    "button_bg": "yellow",
    "description": "A portable Bluetooth speaker with excellent sound quality.",
    "price": 60.00
  },
  {
    "id": 12,
    "picture": "image12.jpg",
    "title": "Coffee Maker",
    "category": "Health",
    "category_bg": "yellow",
    "card_bg": "lightyellow",
    "text_color": "black",
    "button_bg": "yellow",
    "description": "A convenient coffee maker for your perfect morning brew.",
    "price": 100.00
  }
]
